directa_api/__init__.py
directa_api/connection.py
directa_api/errors.py
directa_api/historical.py
directa_api/parsers.py
directa_api/simulation.py
directa_api/trading.py
directa_api_wrapper-0.2.0.dist-info/LICENSE
directa_api_wrapper-0.2.0.dist-info/METADATA
directa_api_wrapper-0.2.0.dist-info/WHEEL
directa_api_wrapper-0.2.0.dist-info/RECORD
