Metadata-Version: 2.3
Name: directa-api-wrapper
Version: 0.2.0
Summary: Python wrapper per l'API di Trading di Directa SIM
Author: Niccolo Salvini
Author-email: 47143429+NiccoloSalvini@users.noreply.github.com
Requires-Python: >=3.9,<4.0
Classifier: Programming Language :: Python :: 3
Classifier: Programming Language :: Python :: 3.9
Classifier: Programming Language :: Python :: 3.10
Classifier: Programming Language :: Python :: 3.11
Classifier: Programming Language :: Python :: 3.12
Classifier: Programming Language :: Python :: 3.13
Requires-Dist: twine (>=6.1.0,<7.0.0)
